{
  "ComponentIndexes": {},
  "ControlUniqueGuids": {},
  "ControlUniqueIds": {
    "actions_1": 163,
    "actions_10": 97,
    "actions_2": 49,
    "actions_3": 33,
    "actions_4": 141,
    "actions_5": 179,
    "actions_6": 125,
    "actions_7": 65,
    "actions_8": 81,
    "actions_9": 17,
    "App": 1,
    "Arrow1": 164,
    "Arrow1_1": 50,
    "Arrow1_2": 34,
    "Arrow1_3": 142,
    "Arrow1_4": 180,
    "Arrow1_5": 126,
    "Arrow1_6": 66,
    "Arrow1_7": 82,
    "Arrow1_8": 18,
    "Arrow1_9": 98,
    "Arrow2_10": 194,
    "Arrow2_11": 195,
    "Arrow2_2": 186,
    "Arrow2_3": 187,
    "Arrow2_4": 188,
    "Arrow2_5": 189,
    "Arrow2_6": 190,
    "Arrow2_7": 191,
    "Arrow2_8": 192,
    "Arrow2_9": 193,
    "Button1": 146,
    "Button1_1": 108,
    "comments_1": 160,
    "comments_10": 94,
    "comments_2": 46,
    "comments_3": 30,
    "comments_4": 138,
    "comments_5": 176,
    "comments_6": 122,
    "comments_7": 62,
    "comments_8": 78,
    "comments_9": 14,
    "email_dg": 107,
    "Image1": 150,
    "Image1_1": 36,
    "Image1_2": 20,
    "Image1_3": 128,
    "Image1_4": 166,
    "Image1_5": 112,
    "Image1_6": 52,
    "Image1_7": 68,
    "Image1_8": 4,
    "Image1_9": 84,
    "Image2": 109,
    "Image2_1": 147,
    "Image3": 110,
    "Image3_1": 148,
    "Label1": 152,
    "Label1_1": 151,
    "Label1_10": 22,
    "Label1_11": 21,
    "Label1_12": 26,
    "Label1_13": 27,
    "Label1_14": 31,
    "Label1_15": 129,
    "Label1_16": 130,
    "Label1_17": 134,
    "Label1_18": 135,
    "Label1_19": 139,
    "Label1_2": 156,
    "Label1_20": 167,
    "Label1_21": 168,
    "Label1_22": 172,
    "Label1_23": 173,
    "Label1_24": 177,
    "Label1_25": 113,
    "Label1_26": 114,
    "Label1_27": 118,
    "Label1_28": 119,
    "Label1_29": 123,
    "Label1_3": 157,
    "Label1_30": 53,
    "Label1_31": 54,
    "Label1_32": 58,
    "Label1_33": 59,
    "Label1_34": 63,
    "Label1_35": 69,
    "Label1_36": 70,
    "Label1_37": 74,
    "Label1_38": 75,
    "Label1_39": 79,
    "Label1_4": 161,
    "Label1_40": 5,
    "Label1_41": 6,
    "Label1_42": 10,
    "Label1_43": 11,
    "Label1_44": 15,
    "Label1_45": 85,
    "Label1_46": 86,
    "Label1_47": 90,
    "Label1_48": 91,
    "Label1_49": 95,
    "Label1_5": 38,
    "Label1_6": 37,
    "Label1_7": 42,
    "Label1_8": 43,
    "Label1_9": 47,
    "Label2": 154,
    "Label2_1": 40,
    "Label2_2": 24,
    "Label2_3": 132,
    "Label2_4": 170,
    "Label2_5": 116,
    "Label2_6": 56,
    "Label2_7": 72,
    "Label2_8": 8,
    "Label2_9": 88,
    "Label3": 153,
    "Label3_1": 39,
    "Label3_2": 23,
    "Label3_3": 131,
    "Label3_4": 169,
    "Label3_5": 115,
    "Label3_6": 55,
    "Label3_7": 71,
    "Label3_8": 7,
    "Label3_9": 87,
    "Label4": 158,
    "Label4_1": 44,
    "Label4_2": 28,
    "Label4_3": 136,
    "Label4_4": 174,
    "Label4_5": 120,
    "Label4_6": 60,
    "Label4_7": 76,
    "Label4_8": 12,
    "Label4_9": 92,
    "Label5": 145,
    "Label5_2": 102,
    "Label5_3": 104,
    "Label5_4": 106,
    "Label6": 100,
    "Label6_1": 144,
    "Label7": 181,
    "money": 105,
    "project": 103,
    "Rectangle1_1": 101,
    "Rectangle2_10": 140,
    "Rectangle2_11": 175,
    "Rectangle2_12": 178,
    "Rectangle2_13": 121,
    "Rectangle2_14": 124,
    "Rectangle2_15": 61,
    "Rectangle2_16": 64,
    "Rectangle2_17": 77,
    "Rectangle2_18": 80,
    "Rectangle2_19": 13,
    "Rectangle2_20": 16,
    "Rectangle2_21": 93,
    "Rectangle2_22": 96,
    "Rectangle2_3": 159,
    "Rectangle2_4": 162,
    "Rectangle2_5": 45,
    "Rectangle2_6": 48,
    "Rectangle2_7": 29,
    "Rectangle2_8": 32,
    "Rectangle2_9": 137,
    "risk_1": 155,
    "risk_10": 89,
    "risk_2": 41,
    "risk_3": 25,
    "risk_4": 133,
    "risk_5": 171,
    "risk_6": 117,
    "risk_7": 57,
    "risk_8": 73,
    "risk_9": 9,
    "Screen1": 149,
    "Screen10": 83,
    "Screen11": 143,
    "Screen12": 99,
    "Screen2": 35,
    "Screen3": 19,
    "Screen4": 127,
    "Screen5": 165,
    "Screen6": 111,
    "Screen7": 51,
    "Screen8": 67,
    "Screen9": 3
  },
  "FunctionParamsInvariantScripts": {},
  "FunctionParamsInvariantScriptsOnInstances": {},
  "HeaderLastSavedDateTimeUTC": "12/05/2022 16:26:37",
  "IsLegacyComponentAllowGlobalScopeCase": false,
  "LocalConnectionIDReferences": {
    "a75c244b-4d19-4884-8489-a347183f2eb6": "\"/providers/microsoft.powerapps/apis/shared_office365/connections/shared-office365-7758f23a-e364-46a2-aee6-9a476dbc15fa\"",
    "e8c8cd39-a479-4d67-83b7-b66b870e1d63": "\"/providers/microsoft.powerapps/apis/shared_logicflows/connections/b9d95fa0-a565-411b-bc4b-dbbd97fe1dfb\""
  },
  "LocalDatabaseReferencesAsEmpty": false,
  "LocalResourceFileNames": {
    "adt_logo": "4eaac67e-81c2-45c3-8caf-a94a6c4cd690.png",
    "adt-logo": "85f4470b-cd1e-47f1-920f-633c13f9a285.png",
    "logotypsa": "e0e74b81-15a6-4642-8f89-bc5bce94fb41.jpg",
    "MicrosoftTeams-image": "0001.png"
  },
  "LocalResourceRootPaths": {
    "adt_logo": "https://docserverpwaprodneu.blob.core.windows.net/3bc91fa7-0dd5-451c-8cab-277900bb41f5-1/resource/Assets0Images04eaac67e-81c2-45c3-8caf-a94a6c4cd690.png?sv=2017-04-17&sr=b&sig=iPwvDkO2nId2Rd%2F905ni0%2FenLV3rApDcXzcZF6kincw%3D&spr=https&se=2022-12-06T15%3A49%3A25Z&sp=r",
    "adt-logo": "https://docserverpwaprodneu.blob.core.windows.net/3bc91fa7-0dd5-451c-8cab-277900bb41f5-1/resource/Assets0Images085f4470b-cd1e-47f1-920f-633c13f9a285.png?sv=2017-04-17&sr=b&sig=8SmzOZzaWRyu6ZeMRSRaFjBa0AsiVffGv%2FsMdLdIId0%3D&spr=https&se=2022-12-06T15%3A49%3A25Z&sp=r",
    "logotypsa": "https://docserverpwaprodneu.blob.core.windows.net/3bc91fa7-0dd5-451c-8cab-277900bb41f5-1/resource/Assets0Images0e0e74b81-15a6-4642-8f89-bc5bce94fb41.jpg?sv=2017-04-17&sr=b&sig=6zvPXzfnJRj0g7hsMAYo4SVmpghCeK67OgResF1pFBU%3D&spr=https&se=2022-12-06T15%3A49%3A25Z&sp=r",
    "MicrosoftTeams-image": "https://docserverpwaprodneu.blob.core.windows.net/3bc91fa7-0dd5-451c-8cab-277900bb41f5-1/resource/Assets0Images00001.png?sv=2017-04-17&sr=b&sig=E6DZAV2FGXK5nzq0Sd0qlAWX%2BnqQOWgPCouTW4n7Rto%3D&spr=https&se=2022-12-06T15%3A49%3A25Z&sp=r"
  },
  "OrderComponentMetadata": {},
  "OrderComponentTemplate": {},
  "OrderDataSource": {
    "colData": 3,
    "ComboBoxSample": 1,
    "dataFlow": 0,
    "DropDownSample": 2
  },
  "OrderGroupControls": {},
  "OrderPcfTemplate": {},
  "OrderTemplate": {},
  "OrderXMLTemplate": {
    "arrow": 5,
    "button": 6,
    "dropdown": 2,
    "image": 0,
    "label": 1,
    "rectangle": 3,
    "text": 4
  },
  "PublishOrderIndices": {
    "actions_1": 24,
    "actions_10": 166,
    "actions_2": 39,
    "actions_3": 55,
    "actions_4": 70,
    "actions_5": 86,
    "actions_6": 102,
    "actions_7": 118,
    "actions_8": 134,
    "actions_9": 150,
    "App": 0,
    "Arrow1": 25,
    "Arrow1_1": 41,
    "Arrow1_2": 56,
    "Arrow1_3": 72,
    "Arrow1_4": 88,
    "Arrow1_5": 104,
    "Arrow1_6": 120,
    "Arrow1_7": 136,
    "Arrow1_8": 152,
    "Arrow1_9": 168,
    "Arrow2_10": 40,
    "Arrow2_11": 40,
    "Arrow2_2": 40,
    "Arrow2_3": 71,
    "Arrow2_4": 87,
    "Arrow2_5": 103,
    "Arrow2_6": 119,
    "Arrow2_7": 135,
    "Arrow2_8": 151,
    "Arrow2_9": 167,
    "Button1": 172,
    "Button1_1": 8,
    "comments_1": 21,
    "comments_10": 163,
    "comments_2": 36,
    "comments_3": 52,
    "comments_4": 67,
    "comments_5": 83,
    "comments_6": 99,
    "comments_7": 115,
    "comments_8": 131,
    "comments_9": 147,
    "email_dg": 7,
    "Image1": 11,
    "Image1_1": 26,
    "Image1_2": 42,
    "Image1_3": 57,
    "Image1_4": 73,
    "Image1_5": 89,
    "Image1_6": 105,
    "Image1_7": 121,
    "Image1_8": 137,
    "Image1_9": 153,
    "Image2": 9,
    "Image2_1": 173,
    "Image3": 10,
    "Image3_1": 174,
    "Label1": 13,
    "Label1_1": 12,
    "Label1_10": 44,
    "Label1_11": 43,
    "Label1_12": 48,
    "Label1_13": 49,
    "Label1_14": 53,
    "Label1_15": 58,
    "Label1_16": 59,
    "Label1_17": 63,
    "Label1_18": 64,
    "Label1_19": 68,
    "Label1_2": 17,
    "Label1_20": 74,
    "Label1_21": 75,
    "Label1_22": 79,
    "Label1_23": 80,
    "Label1_24": 84,
    "Label1_25": 90,
    "Label1_26": 91,
    "Label1_27": 95,
    "Label1_28": 96,
    "Label1_29": 100,
    "Label1_3": 18,
    "Label1_30": 106,
    "Label1_31": 107,
    "Label1_32": 111,
    "Label1_33": 112,
    "Label1_34": 116,
    "Label1_35": 122,
    "Label1_36": 123,
    "Label1_37": 127,
    "Label1_38": 128,
    "Label1_39": 132,
    "Label1_4": 22,
    "Label1_40": 138,
    "Label1_41": 139,
    "Label1_42": 143,
    "Label1_43": 144,
    "Label1_44": 148,
    "Label1_45": 154,
    "Label1_46": 155,
    "Label1_47": 159,
    "Label1_48": 160,
    "Label1_49": 164,
    "Label1_5": 28,
    "Label1_6": 27,
    "Label1_7": 32,
    "Label1_8": 33,
    "Label1_9": 37,
    "Label2": 15,
    "Label2_1": 30,
    "Label2_2": 46,
    "Label2_3": 61,
    "Label2_4": 77,
    "Label2_5": 93,
    "Label2_6": 109,
    "Label2_7": 125,
    "Label2_8": 141,
    "Label2_9": 157,
    "Label3": 14,
    "Label3_1": 29,
    "Label3_2": 45,
    "Label3_3": 60,
    "Label3_4": 76,
    "Label3_5": 92,
    "Label3_6": 108,
    "Label3_7": 124,
    "Label3_8": 140,
    "Label3_9": 156,
    "Label4": 19,
    "Label4_1": 34,
    "Label4_2": 50,
    "Label4_3": 65,
    "Label4_4": 81,
    "Label4_5": 97,
    "Label4_6": 113,
    "Label4_7": 129,
    "Label4_8": 145,
    "Label4_9": 161,
    "Label5": 170,
    "Label5_2": 2,
    "Label5_3": 4,
    "Label5_4": 6,
    "Label6": 0,
    "Label6_1": 169,
    "Label7": 171,
    "money": 5,
    "project": 3,
    "Rectangle1_1": 1,
    "Rectangle2_10": 69,
    "Rectangle2_11": 82,
    "Rectangle2_12": 85,
    "Rectangle2_13": 98,
    "Rectangle2_14": 101,
    "Rectangle2_15": 114,
    "Rectangle2_16": 117,
    "Rectangle2_17": 130,
    "Rectangle2_18": 133,
    "Rectangle2_19": 146,
    "Rectangle2_20": 149,
    "Rectangle2_21": 162,
    "Rectangle2_22": 165,
    "Rectangle2_3": 20,
    "Rectangle2_4": 23,
    "Rectangle2_5": 35,
    "Rectangle2_6": 38,
    "Rectangle2_7": 51,
    "Rectangle2_8": 54,
    "Rectangle2_9": 66,
    "risk_1": 16,
    "risk_10": 158,
    "risk_2": 31,
    "risk_3": 47,
    "risk_4": 62,
    "risk_5": 78,
    "risk_6": 94,
    "risk_7": 110,
    "risk_8": 126,
    "risk_9": 142,
    "Screen1": 2,
    "Screen10": 18,
    "Screen11": 0,
    "Screen12": 34,
    "Screen2": 47,
    "Screen3": 63,
    "Screen4": 79,
    "Screen5": 95,
    "Screen6": 111,
    "Screen7": 127,
    "Screen8": 143,
    "Screen9": 159
  },
  "ResourcesJsonIndices": {
    "Image-adt_logo": 2,
    "Image-adt-logo": 3,
    "Image-logotypsa": 4,
    "Image-MicrosoftTeams-image": 1,
    "Image-SampleImage": 0
  },
  "RuleScreenIdWithoutScreen": {},
  "TemplateVersions": {},
  "VolatileProperties": {
    "AnalysisLoadTime": 1.7169214,
    "ControlCount": {
      "arrow": 22,
      "button": 2,
      "dropdown": 10,
      "image": 14,
      "label": 86,
      "rectangle": 21,
      "screen": 12,
      "text": 23
    },
    "DeserializationLoadTime": 3.8306763,
    "ErrorCount": 0
  },
  "WasLocalDatabaseReferencesEmpty": false
}