{
  "ComponentIndexes": {},
  "ControlUniqueGuids": {},
  "ControlUniqueIds": {
    "actions_1": 105,
    "actions_10": 51,
    "actions_2": 17,
    "actions_3": 156,
    "actions_4": 81,
    "actions_5": 139,
    "actions_6": 122,
    "actions_7": 190,
    "actions_8": 34,
    "actions_9": 173,
    "App": 1,
    "Arrow1": 107,
    "Arrow1_1": 19,
    "Arrow1_2": 158,
    "Arrow1_3": 83,
    "Arrow1_4": 141,
    "Arrow1_5": 124,
    "Arrow1_6": 192,
    "Arrow1_7": 36,
    "Arrow1_8": 175,
    "Arrow1_9": 53,
    "Arrow2_10": 106,
    "Arrow2_11": 157,
    "Arrow2_2": 18,
    "Arrow2_3": 82,
    "Arrow2_4": 140,
    "Arrow2_5": 123,
    "Arrow2_6": 191,
    "Arrow2_7": 35,
    "Arrow2_8": 174,
    "Arrow2_9": 52,
    "Button1": 88,
    "Button1_1": 66,
    "comments_1": 102,
    "comments_10": 48,
    "comments_2": 14,
    "comments_3": 153,
    "comments_4": 78,
    "comments_5": 136,
    "comments_6": 119,
    "comments_7": 187,
    "comments_8": 31,
    "comments_9": 170,
    "Datos_generales": 54,
    "email_dg": 62,
    "Enviar_formulario": 84,
    "Image1": 92,
    "Image1_1": 4,
    "Image1_2": 143,
    "Image1_3": 68,
    "Image1_4": 126,
    "Image1_5": 109,
    "Image1_6": 177,
    "Image1_7": 21,
    "Image1_8": 160,
    "Image1_9": 38,
    "Image2": 56,
    "Image2_1": 89,
    "Image3": 57,
    "Image3_1": 90,
    "Label1": 94,
    "Label1_1": 93,
    "Label1_10": 145,
    "Label1_11": 144,
    "Label1_12": 149,
    "Label1_13": 150,
    "Label1_14": 154,
    "Label1_15": 69,
    "Label1_16": 70,
    "Label1_17": 74,
    "Label1_18": 75,
    "Label1_19": 79,
    "Label1_2": 98,
    "Label1_20": 127,
    "Label1_21": 128,
    "Label1_22": 132,
    "Label1_23": 133,
    "Label1_24": 137,
    "Label1_25": 110,
    "Label1_26": 111,
    "Label1_27": 115,
    "Label1_28": 116,
    "Label1_29": 120,
    "Label1_3": 99,
    "Label1_30": 178,
    "Label1_31": 179,
    "Label1_32": 183,
    "Label1_33": 184,
    "Label1_34": 188,
    "Label1_35": 22,
    "Label1_36": 23,
    "Label1_37": 27,
    "Label1_38": 28,
    "Label1_39": 32,
    "Label1_4": 103,
    "Label1_40": 161,
    "Label1_41": 162,
    "Label1_42": 166,
    "Label1_43": 167,
    "Label1_44": 171,
    "Label1_45": 39,
    "Label1_46": 40,
    "Label1_47": 44,
    "Label1_48": 45,
    "Label1_49": 49,
    "Label1_5": 6,
    "Label1_6": 5,
    "Label1_7": 10,
    "Label1_8": 11,
    "Label1_9": 15,
    "Label2": 96,
    "Label2_1": 8,
    "Label2_2": 147,
    "Label2_3": 72,
    "Label2_4": 130,
    "Label2_5": 113,
    "Label2_6": 181,
    "Label2_7": 25,
    "Label2_8": 164,
    "Label2_9": 42,
    "Label3": 95,
    "Label3_1": 7,
    "Label3_2": 146,
    "Label3_3": 71,
    "Label3_4": 129,
    "Label3_5": 112,
    "Label3_6": 180,
    "Label3_7": 24,
    "Label3_8": 163,
    "Label3_9": 41,
    "Label4": 100,
    "Label4_1": 12,
    "Label4_2": 151,
    "Label4_3": 76,
    "Label4_4": 134,
    "Label4_5": 117,
    "Label4_6": 185,
    "Label4_7": 29,
    "Label4_8": 168,
    "Label4_9": 46,
    "Label5": 86,
    "Label5_2": 59,
    "Label5_3": 64,
    "Label5_4": 60,
    "Label6": 55,
    "Label6_1": 85,
    "Label7": 87,
    "Label8": 193,
    "ListBox1": 63,
    "money": 65,
    "project": 61,
    "Rectangle1_1": 58,
    "Rectangle2_10": 80,
    "Rectangle2_11": 135,
    "Rectangle2_12": 138,
    "Rectangle2_13": 118,
    "Rectangle2_14": 121,
    "Rectangle2_15": 186,
    "Rectangle2_16": 189,
    "Rectangle2_17": 30,
    "Rectangle2_18": 33,
    "Rectangle2_19": 169,
    "Rectangle2_20": 172,
    "Rectangle2_21": 47,
    "Rectangle2_22": 50,
    "Rectangle2_3": 101,
    "Rectangle2_4": 104,
    "Rectangle2_5": 13,
    "Rectangle2_6": 16,
    "Rectangle2_7": 152,
    "Rectangle2_8": 155,
    "Rectangle2_9": 77,
    "risk_1": 97,
    "risk_10": 43,
    "risk_2": 9,
    "risk_3": 148,
    "risk_4": 73,
    "risk_5": 131,
    "risk_6": 114,
    "risk_7": 182,
    "risk_8": 26,
    "risk_9": 165,
    "RT-01": 91,
    "RT-02": 3,
    "RT-03": 142,
    "RT-04": 67,
    "RT-05": 125,
    "RT-06": 108,
    "RT-07": 176,
    "RT-08": 20,
    "RT-09": 159,
    "RT-10": 37
  },
  "FunctionParamsInvariantScripts": {},
  "FunctionParamsInvariantScriptsOnInstances": {},
  "HeaderLastSavedDateTimeUTC": "12/10/2022 20:36:35",
  "IsLegacyComponentAllowGlobalScopeCase": false,
  "LocalConnectionIDReferences": {
    "0c07a5b4-d0a2-47f2-b9d6-d55d38055230": "\"/providers/microsoft.powerapps/apis/shared_office365users/connections/shared-office365user-fb127bc8-31f8-4039-ad05-7dd5694cf316\"",
    "a75c244b-4d19-4884-8489-a347183f2eb6": "\"/providers/microsoft.powerapps/apis/shared_office365/connections/shared-office365-00aabbce-aede-4357-9f24-0868cf392e07\"",
    "e8c8cd39-a479-4d67-83b7-b66b870e1d63": "\"/providers/microsoft.powerapps/apis/shared_logicflows/connections/21178a7cd347439a934d2118350cb2a4\""
  },
  "LocalDatabaseReferencesAsEmpty": false,
  "LocalResourceFileNames": {
    "adt_logo": "4eaac67e-81c2-45c3-8caf-a94a6c4cd690.png",
    "adt-logo": "85f4470b-cd1e-47f1-920f-633c13f9a285.png",
    "logotypsa": "e0e74b81-15a6-4642-8f89-bc5bce94fb41.jpg",
    "MicrosoftTeams-image": "0001.png"
  },
  "LocalResourceRootPaths": {
    "adt_logo": "https://docserverpwaprodweu.blob.core.windows.net/b2b896b3-0c8f-482a-8043-99f3a6dbf3c5-1/resource/Assets0Images04eaac67e-81c2-45c3-8caf-a94a6c4cd690.png?sv=2017-04-17&sr=b&sig=dmNS6pY3tUv%2F%2Bv0cqA8O8ThZlCHPqRMIQHu1uQrk2AY%3D&spr=https&se=2022-12-11T20%3A36%3A55Z&sp=r",
    "adt-logo": "https://docserverpwaprodweu.blob.core.windows.net/b2b896b3-0c8f-482a-8043-99f3a6dbf3c5-1/resource/Assets0Images085f4470b-cd1e-47f1-920f-633c13f9a285.png?sv=2017-04-17&sr=b&sig=itbDyQ2Trpfe1cWkt1l0N%2FKJLlGQolXPkcZmUeChMcs%3D&spr=https&se=2022-12-11T20%3A36%3A55Z&sp=r",
    "logotypsa": "https://docserverpwaprodweu.blob.core.windows.net/b2b896b3-0c8f-482a-8043-99f3a6dbf3c5-1/resource/Assets0Images0e0e74b81-15a6-4642-8f89-bc5bce94fb41.jpg?sv=2017-04-17&sr=b&sig=VtebrMs7p%2B9UHOfX1UzIrjSAANXKuFRr9O5EnsS1p1A%3D&spr=https&se=2022-12-11T20%3A36%3A55Z&sp=r",
    "MicrosoftTeams-image": "https://docserverpwaprodweu.blob.core.windows.net/b2b896b3-0c8f-482a-8043-99f3a6dbf3c5-1/resource/Assets0Images00001.png?sv=2017-04-17&sr=b&sig=JX7fWid3n1OyLUyagzqO%2FVicShpy%2B1Fli%2BURBlnP9RY%3D&spr=https&se=2022-12-11T20%3A36%3A55Z&sp=r"
  },
  "OrderComponentMetadata": {},
  "OrderComponentTemplate": {},
  "OrderDataSource": {
    "colData": 6,
    "ComboBoxSample": 2,
    "dataFlow": 0,
    "DropDownSample": 3,
    "ListboxSample": 5,
    "Office365Users": 1,
    "RadioSample": 4
  },
  "OrderGroupControls": {},
  "OrderPcfTemplate": {},
  "OrderTemplate": {},
  "OrderXMLTemplate": {
    "arrow": 5,
    "button": 7,
    "dropdown": 2,
    "image": 0,
    "label": 1,
    "listbox": 6,
    "rectangle": 3,
    "text": 4
  },
  "PublishOrderIndices": {
    "actions_1": 26,
    "actions_10": 170,
    "actions_2": 42,
    "actions_3": 58,
    "actions_4": 74,
    "actions_5": 90,
    "actions_6": 106,
    "actions_7": 122,
    "actions_8": 138,
    "actions_9": 154,
    "App": 0,
    "Arrow1": 28,
    "Arrow1_1": 44,
    "Arrow1_2": 60,
    "Arrow1_3": 76,
    "Arrow1_4": 92,
    "Arrow1_5": 108,
    "Arrow1_6": 124,
    "Arrow1_7": 140,
    "Arrow1_8": 156,
    "Arrow1_9": 172,
    "Arrow2_10": 27,
    "Arrow2_11": 59,
    "Arrow2_2": 43,
    "Arrow2_3": 75,
    "Arrow2_4": 91,
    "Arrow2_5": 107,
    "Arrow2_6": 123,
    "Arrow2_7": 139,
    "Arrow2_8": 155,
    "Arrow2_9": 171,
    "Button1": 176,
    "Button1_1": 12,
    "comments_1": 23,
    "comments_10": 167,
    "comments_2": 39,
    "comments_3": 55,
    "comments_4": 71,
    "comments_5": 87,
    "comments_6": 103,
    "comments_7": 119,
    "comments_8": 135,
    "comments_9": 151,
    "Datos_generales": 34,
    "email_dg": 7,
    "Enviar_formulario": 0,
    "Image1": 13,
    "Image1_1": 29,
    "Image1_2": 45,
    "Image1_3": 61,
    "Image1_4": 77,
    "Image1_5": 93,
    "Image1_6": 109,
    "Image1_7": 125,
    "Image1_8": 141,
    "Image1_9": 157,
    "Image2": 0,
    "Image2_1": 177,
    "Image3": 1,
    "Image3_1": 178,
    "Label1": 15,
    "Label1_1": 14,
    "Label1_10": 47,
    "Label1_11": 46,
    "Label1_12": 51,
    "Label1_13": 52,
    "Label1_14": 56,
    "Label1_15": 62,
    "Label1_16": 63,
    "Label1_17": 67,
    "Label1_18": 68,
    "Label1_19": 72,
    "Label1_2": 19,
    "Label1_20": 78,
    "Label1_21": 79,
    "Label1_22": 83,
    "Label1_23": 84,
    "Label1_24": 88,
    "Label1_25": 94,
    "Label1_26": 95,
    "Label1_27": 99,
    "Label1_28": 100,
    "Label1_29": 104,
    "Label1_3": 20,
    "Label1_30": 110,
    "Label1_31": 111,
    "Label1_32": 115,
    "Label1_33": 116,
    "Label1_34": 120,
    "Label1_35": 126,
    "Label1_36": 127,
    "Label1_37": 131,
    "Label1_38": 132,
    "Label1_39": 136,
    "Label1_4": 24,
    "Label1_40": 142,
    "Label1_41": 143,
    "Label1_42": 147,
    "Label1_43": 148,
    "Label1_44": 152,
    "Label1_45": 158,
    "Label1_46": 159,
    "Label1_47": 163,
    "Label1_48": 164,
    "Label1_49": 168,
    "Label1_5": 31,
    "Label1_6": 30,
    "Label1_7": 35,
    "Label1_8": 36,
    "Label1_9": 40,
    "Label2": 17,
    "Label2_1": 33,
    "Label2_2": 49,
    "Label2_3": 65,
    "Label2_4": 81,
    "Label2_5": 97,
    "Label2_6": 113,
    "Label2_7": 129,
    "Label2_8": 145,
    "Label2_9": 161,
    "Label3": 16,
    "Label3_1": 32,
    "Label3_2": 48,
    "Label3_3": 64,
    "Label3_4": 80,
    "Label3_5": 96,
    "Label3_6": 112,
    "Label3_7": 128,
    "Label3_8": 144,
    "Label3_9": 160,
    "Label4": 21,
    "Label4_1": 37,
    "Label4_2": 53,
    "Label4_3": 69,
    "Label4_4": 85,
    "Label4_5": 101,
    "Label4_6": 117,
    "Label4_7": 133,
    "Label4_8": 149,
    "Label4_9": 165,
    "Label5": 174,
    "Label5_2": 4,
    "Label5_3": 9,
    "Label5_4": 5,
    "Label6": 2,
    "Label6_1": 173,
    "Label7": 175,
    "Label8": 11,
    "ListBox1": 8,
    "money": 10,
    "project": 6,
    "Rectangle1_1": 3,
    "Rectangle2_10": 73,
    "Rectangle2_11": 86,
    "Rectangle2_12": 89,
    "Rectangle2_13": 102,
    "Rectangle2_14": 105,
    "Rectangle2_15": 118,
    "Rectangle2_16": 121,
    "Rectangle2_17": 134,
    "Rectangle2_18": 137,
    "Rectangle2_19": 150,
    "Rectangle2_20": 153,
    "Rectangle2_21": 166,
    "Rectangle2_22": 169,
    "Rectangle2_3": 22,
    "Rectangle2_4": 25,
    "Rectangle2_5": 38,
    "Rectangle2_6": 41,
    "Rectangle2_7": 54,
    "Rectangle2_8": 57,
    "Rectangle2_9": 70,
    "risk_1": 18,
    "risk_10": 162,
    "risk_2": 34,
    "risk_3": 50,
    "risk_4": 66,
    "risk_5": 82,
    "risk_6": 98,
    "risk_7": 114,
    "risk_8": 130,
    "risk_9": 146,
    "RT-01": 2,
    "RT-02": 47,
    "RT-03": 63,
    "RT-04": 79,
    "RT-05": 95,
    "RT-06": 111,
    "RT-07": 127,
    "RT-08": 143,
    "RT-09": 159,
    "RT-10": 18
  },
  "ResourcesJsonIndices": {
    "Image-adt_logo": 2,
    "Image-adt-logo": 3,
    "Image-logotypsa": 4,
    "Image-MicrosoftTeams-image": 1,
    "Image-SampleImage": 0
  },
  "RuleScreenIdWithoutScreen": {},
  "TemplateVersions": {},
  "VolatileProperties": {
    "AnalysisLoadTime": 1.58926,
    "ControlCount": {
      "arrow": 20,
      "button": 2,
      "dropdown": 10,
      "image": 14,
      "label": 87,
      "listbox": 1,
      "rectangle": 21,
      "screen": 12,
      "text": 23
    },
    "DeserializationLoadTime": 5.046342,
    "ErrorCount": 0
  },
  "WasLocalDatabaseReferencesEmpty": false
}